dbc_parse/__init__.py
dbc_parse/dbc.py
dbc_parse-1.0.12.dist-info/LICENSE.txt
dbc_parse-1.0.12.dist-info/METADATA
dbc_parse-1.0.12.dist-info/WHEEL
dbc_parse-1.0.12.dist-info/top_level.txt
dbc_parse-1.0.12.dist-info/RECORD
